{
  "node_modules/@sveltejs/kit/src/runtime/client/start.js": {
    "file": "_app/immutable/start-366219bc.js",
    "src": "node_modules/@sveltejs/kit/src/runtime/client/start.js",
    "isEntry": true,
    "imports": [
      "_index-f9721e3d.js",
      "_singletons-70974112.js"
    ],
    "dynamicImports": [
      ".svelte-kit/generated/nodes/0.js",
      ".svelte-kit/generated/nodes/1.js",
      ".svelte-kit/generated/nodes/2.js",
      ".svelte-kit/generated/nodes/3.js",
      ".svelte-kit/generated/nodes/4.js",
      ".svelte-kit/generated/nodes/5.js",
      ".svelte-kit/generated/nodes/6.js",
      ".svelte-kit/generated/nodes/7.js",
      ".svelte-kit/generated/nodes/8.js",
      ".svelte-kit/generated/nodes/9.js",
      ".svelte-kit/generated/nodes/10.js",
      ".svelte-kit/generated/nodes/11.js"
    ]
  },
  "src/routes/+layout.svelte": {
    "file": "_app/immutable/components/pages/_layout.svelte-1dff84f3.js",
    "src": "src/routes/+layout.svelte",
    "isEntry": true,
    "imports": [
      "_index-f9721e3d.js",
      "_width-fd20bcd4.js",
      "_FontAwesomeIcon-f906f5dd.js",
      "_TrackedLink-2f935d9a.js"
    ],
    "css": [
      "_app/immutable/assets/_layout-2ee860c0.css"
    ]
  },
  "node_modules/@sveltejs/kit/src/runtime/components/error.svelte": {
    "file": "_app/immutable/components/error.svelte-04d89c44.js",
    "src": "node_modules/@sveltejs/kit/src/runtime/components/error.svelte",
    "isEntry": true,
    "imports": [
      "_index-f9721e3d.js",
      "_stores-a8e4c5a4.js",
      "_singletons-70974112.js"
    ]
  },
  "src/routes/+page.svelte": {
    "file": "_app/immutable/components/pages/_page.svelte-4d50cb87.js",
    "src": "src/routes/+page.svelte",
    "isEntry": true,
    "imports": [
      "_index-f9721e3d.js",
      "_NotificationLink-778b52ee.js",
      "_PageHeader-17c79210.js",
      "_TrackedLink-2f935d9a.js",
      "_width-fd20bcd4.js",
      "_stores-a8e4c5a4.js",
      "_singletons-70974112.js"
    ]
  },
  "src/routes/about/+page.svelte": {
    "file": "_app/immutable/components/pages/about/_page.svelte-0780ee8e.js",
    "src": "src/routes/about/+page.svelte",
    "isEntry": true,
    "imports": [
      "_index-f9721e3d.js",
      "_NotificationLink-778b52ee.js",
      "_PageHeader-17c79210.js",
      "_stores-a8e4c5a4.js",
      "_singletons-70974112.js",
      "_width-fd20bcd4.js"
    ]
  },
  "src/routes/about/committee/+page.svelte": {
    "file": "_app/immutable/components/pages/about/committee/_page.svelte-5b94e1fd.js",
    "src": "src/routes/about/committee/+page.svelte",
    "isEntry": true,
    "imports": [
      "_index-f9721e3d.js",
      "_PageHeader-17c79210.js",
      "_width-fd20bcd4.js"
    ],
    "css": [
      "_app/immutable/assets/_page-a2ddf001.css"
    ]
  },
  "src/routes/about/constitution-and-guidelines/+page.svelte": {
    "file": "_app/immutable/components/pages/about/constitution-and-guidelines/_page.svelte-1ccf08c1.js",
    "src": "src/routes/about/constitution-and-guidelines/+page.svelte",
    "isEntry": true,
    "imports": [
      "_index-f9721e3d.js",
      "_Content-b04c1811.js",
      "_PageHeader-17c79210.js",
      "_width-fd20bcd4.js"
    ]
  },
  "src/routes/about/meetings/+page.svelte": {
    "file": "_app/immutable/components/pages/about/meetings/_page.svelte-7f204a9f.js",
    "src": "src/routes/about/meetings/+page.svelte",
    "isEntry": true,
    "imports": [
      "_index-f9721e3d.js",
      "_Content-b04c1811.js",
      "_TrackedLink-2f935d9a.js",
      "_PageHeader-17c79210.js",
      "_width-fd20bcd4.js"
    ]
  },
  "src/routes/get-involved/+page.svelte": {
    "file": "_app/immutable/components/pages/get-involved/_page.svelte-6172626a.js",
    "src": "src/routes/get-involved/+page.svelte",
    "isEntry": true,
    "imports": [
      "_index-f9721e3d.js",
      "_NotificationLink-778b52ee.js",
      "_PageHeader-17c79210.js",
      "_stores-a8e4c5a4.js",
      "_singletons-70974112.js",
      "_width-fd20bcd4.js"
    ]
  },
  "src/routes/get-involved/freshers/+page.svelte": {
    "file": "_app/immutable/components/pages/get-involved/freshers/_page.svelte-d3608020.js",
    "src": "src/routes/get-involved/freshers/+page.svelte",
    "isEntry": true,
    "imports": [
      "_index-f9721e3d.js",
      "_Content-b04c1811.js",
      "_PageHeader-17c79210.js",
      "_width-fd20bcd4.js"
    ],
    "css": [
      "_app/immutable/assets/_page-e5f8ff0b.css"
    ]
  },
  "src/routes/get-involved/societies/+page.svelte": {
    "file": "_app/immutable/components/pages/get-involved/societies/_page.svelte-63369204.js",
    "src": "src/routes/get-involved/societies/+page.svelte",
    "isEntry": true,
    "imports": [
      "_index-f9721e3d.js",
      "_Content-b04c1811.js",
      "_PageHeader-17c79210.js",
      "_FontAwesomeIcon-f906f5dd.js",
      "_Markdown-027b6ef9.js",
      "_width-fd20bcd4.js"
    ]
  },
  "src/routes/resources/+page.svelte": {
    "file": "_app/immutable/components/pages/resources/_page.svelte-164c31ae.js",
    "src": "src/routes/resources/+page.svelte",
    "isEntry": true,
    "imports": [
      "_index-f9721e3d.js",
      "_NotificationLink-778b52ee.js",
      "_PageHeader-17c79210.js",
      "_stores-a8e4c5a4.js",
      "_singletons-70974112.js",
      "_width-fd20bcd4.js"
    ]
  },
  "src/routes/resources/[heading]/+page.svelte": {
    "file": "_app/immutable/components/pages/resources/_heading_/_page.svelte-765424a6.js",
    "src": "src/routes/resources/[heading]/+page.svelte",
    "isEntry": true,
    "imports": [
      "_index-f9721e3d.js",
      "_stores-a8e4c5a4.js",
      "_Markdown-027b6ef9.js",
      "_PageHeader-17c79210.js",
      "_singletons-70974112.js",
      "_width-fd20bcd4.js"
    ],
    "css": [
      "_app/immutable/assets/_page-8c93789c.css"
    ]
  },
  "src/routes/+layout.js": {
    "file": "_app/immutable/modules/pages/_layout.js-7b9cbfbc.js",
    "src": "src/routes/+layout.js",
    "isEntry": true,
    "imports": [
      "__layout-8d2a742b.js"
    ]
  },
  "_singletons-70974112.js": {
    "file": "_app/immutable/chunks/singletons-70974112.js",
    "imports": [
      "_index-f9721e3d.js"
    ]
  },
  "_index-f9721e3d.js": {
    "file": "_app/immutable/chunks/index-f9721e3d.js"
  },
  "_FontAwesomeIcon-f906f5dd.js": {
    "file": "_app/immutable/chunks/FontAwesomeIcon-f906f5dd.js",
    "imports": [
      "_index-f9721e3d.js"
    ]
  },
  "_TrackedLink-2f935d9a.js": {
    "file": "_app/immutable/chunks/TrackedLink-2f935d9a.js",
    "imports": [
      "_index-f9721e3d.js"
    ]
  },
  "_width-fd20bcd4.js": {
    "file": "_app/immutable/chunks/width-fd20bcd4.js",
    "imports": [
      "_index-f9721e3d.js"
    ]
  },
  "__layout-8d2a742b.js": {
    "file": "_app/immutable/chunks/_layout-8d2a742b.js"
  },
  "_stores-a8e4c5a4.js": {
    "file": "_app/immutable/chunks/stores-a8e4c5a4.js",
    "imports": [
      "_index-f9721e3d.js",
      "_singletons-70974112.js"
    ]
  },
  "_NotificationLink-778b52ee.js": {
    "file": "_app/immutable/chunks/NotificationLink-778b52ee.js",
    "imports": [
      "_index-f9721e3d.js",
      "_stores-a8e4c5a4.js"
    ],
    "css": [
      "_app/immutable/assets/NotificationLink-24e04704.css"
    ]
  },
  "_PageHeader-17c79210.js": {
    "file": "_app/immutable/chunks/PageHeader-17c79210.js",
    "imports": [
      "_index-f9721e3d.js",
      "_width-fd20bcd4.js"
    ],
    "css": [
      "_app/immutable/assets/PageHeader-25283914.css"
    ]
  },
  "_Content-b04c1811.js": {
    "file": "_app/immutable/chunks/Content-b04c1811.js",
    "imports": [
      "_index-f9721e3d.js"
    ]
  },
  "_Markdown-027b6ef9.js": {
    "file": "_app/immutable/chunks/Markdown-027b6ef9.js",
    "imports": [
      "_index-f9721e3d.js"
    ]
  },
  ".svelte-kit/generated/nodes/0.js": {
    "file": "_app/immutable/chunks/0-21ca9f48.js",
    "src": ".svelte-kit/generated/nodes/0.js",
    "isDynamicEntry": true,
    "imports": [
      "__layout-8d2a742b.js",
      "src/routes/+layout.svelte",
      "_index-f9721e3d.js",
      "_width-fd20bcd4.js",
      "_FontAwesomeIcon-f906f5dd.js",
      "_TrackedLink-2f935d9a.js"
    ]
  },
  ".svelte-kit/generated/nodes/1.js": {
    "file": "_app/immutable/chunks/1-80158eb6.js",
    "src": ".svelte-kit/generated/nodes/1.js",
    "isDynamicEntry": true,
    "imports": [
      "node_modules/@sveltejs/kit/src/runtime/components/error.svelte",
      "_index-f9721e3d.js",
      "_stores-a8e4c5a4.js",
      "_singletons-70974112.js"
    ]
  },
  ".svelte-kit/generated/nodes/2.js": {
    "file": "_app/immutable/chunks/2-ca03c9e3.js",
    "src": ".svelte-kit/generated/nodes/2.js",
    "isDynamicEntry": true,
    "imports": [
      "src/routes/+page.svelte",
      "_index-f9721e3d.js",
      "_NotificationLink-778b52ee.js",
      "_stores-a8e4c5a4.js",
      "_singletons-70974112.js",
      "_PageHeader-17c79210.js",
      "_width-fd20bcd4.js",
      "_TrackedLink-2f935d9a.js"
    ]
  },
  ".svelte-kit/generated/nodes/3.js": {
    "file": "_app/immutable/chunks/3-5196b1bf.js",
    "src": ".svelte-kit/generated/nodes/3.js",
    "isDynamicEntry": true,
    "imports": [
      "src/routes/about/+page.svelte",
      "_index-f9721e3d.js",
      "_NotificationLink-778b52ee.js",
      "_stores-a8e4c5a4.js",
      "_singletons-70974112.js",
      "_PageHeader-17c79210.js",
      "_width-fd20bcd4.js"
    ]
  },
  ".svelte-kit/generated/nodes/4.js": {
    "file": "_app/immutable/chunks/4-66c93004.js",
    "src": ".svelte-kit/generated/nodes/4.js",
    "isDynamicEntry": true,
    "imports": [
      "src/routes/about/committee/+page.svelte",
      "_index-f9721e3d.js",
      "_PageHeader-17c79210.js",
      "_width-fd20bcd4.js"
    ]
  },
  ".svelte-kit/generated/nodes/5.js": {
    "file": "_app/immutable/chunks/5-665a4c9e.js",
    "src": ".svelte-kit/generated/nodes/5.js",
    "isDynamicEntry": true,
    "imports": [
      "src/routes/about/constitution-and-guidelines/+page.svelte",
      "_index-f9721e3d.js",
      "_Content-b04c1811.js",
      "_PageHeader-17c79210.js",
      "_width-fd20bcd4.js"
    ]
  },
  ".svelte-kit/generated/nodes/6.js": {
    "file": "_app/immutable/chunks/6-cc5ce9f4.js",
    "src": ".svelte-kit/generated/nodes/6.js",
    "isDynamicEntry": true,
    "imports": [
      "src/routes/about/meetings/+page.svelte",
      "_index-f9721e3d.js",
      "_Content-b04c1811.js",
      "_TrackedLink-2f935d9a.js",
      "_PageHeader-17c79210.js",
      "_width-fd20bcd4.js"
    ]
  },
  ".svelte-kit/generated/nodes/7.js": {
    "file": "_app/immutable/chunks/7-2a47304f.js",
    "src": ".svelte-kit/generated/nodes/7.js",
    "isDynamicEntry": true,
    "imports": [
      "src/routes/get-involved/+page.svelte",
      "_index-f9721e3d.js",
      "_NotificationLink-778b52ee.js",
      "_stores-a8e4c5a4.js",
      "_singletons-70974112.js",
      "_PageHeader-17c79210.js",
      "_width-fd20bcd4.js"
    ]
  },
  ".svelte-kit/generated/nodes/8.js": {
    "file": "_app/immutable/chunks/8-a0e83a48.js",
    "src": ".svelte-kit/generated/nodes/8.js",
    "isDynamicEntry": true,
    "imports": [
      "src/routes/get-involved/freshers/+page.svelte",
      "_index-f9721e3d.js",
      "_Content-b04c1811.js",
      "_PageHeader-17c79210.js",
      "_width-fd20bcd4.js"
    ]
  },
  ".svelte-kit/generated/nodes/9.js": {
    "file": "_app/immutable/chunks/9-44db9d34.js",
    "src": ".svelte-kit/generated/nodes/9.js",
    "isDynamicEntry": true,
    "imports": [
      "src/routes/get-involved/societies/+page.svelte",
      "_index-f9721e3d.js",
      "_Content-b04c1811.js",
      "_PageHeader-17c79210.js",
      "_width-fd20bcd4.js",
      "_FontAwesomeIcon-f906f5dd.js",
      "_Markdown-027b6ef9.js"
    ]
  },
  ".svelte-kit/generated/nodes/10.js": {
    "file": "_app/immutable/chunks/10-3bb0ac31.js",
    "src": ".svelte-kit/generated/nodes/10.js",
    "isDynamicEntry": true,
    "imports": [
      "src/routes/resources/+page.svelte",
      "_index-f9721e3d.js",
      "_NotificationLink-778b52ee.js",
      "_stores-a8e4c5a4.js",
      "_singletons-70974112.js",
      "_PageHeader-17c79210.js",
      "_width-fd20bcd4.js"
    ]
  },
  ".svelte-kit/generated/nodes/11.js": {
    "file": "_app/immutable/chunks/11-72b3f566.js",
    "src": ".svelte-kit/generated/nodes/11.js",
    "isDynamicEntry": true,
    "imports": [
      "src/routes/resources/[heading]/+page.svelte",
      "_index-f9721e3d.js",
      "_stores-a8e4c5a4.js",
      "_singletons-70974112.js",
      "_Markdown-027b6ef9.js",
      "_PageHeader-17c79210.js",
      "_width-fd20bcd4.js"
    ]
  },
  "NotificationLink.css": {
    "file": "_app/immutable/assets/NotificationLink-24e04704.css",
    "src": "NotificationLink.css"
  },
  "src/routes/about/committee/+page.css": {
    "file": "_app/immutable/assets/_page-a2ddf001.css",
    "src": "src/routes/about/committee/+page.css"
  },
  "src/routes/resources/[heading]/+page.css": {
    "file": "_app/immutable/assets/_page-8c93789c.css",
    "src": "src/routes/resources/[heading]/+page.css"
  },
  "PageHeader.css": {
    "file": "_app/immutable/assets/PageHeader-25283914.css",
    "src": "PageHeader.css"
  },
  "src/routes/get-involved/freshers/+page.css": {
    "file": "_app/immutable/assets/_page-e5f8ff0b.css",
    "src": "src/routes/get-involved/freshers/+page.css"
  },
  "src/routes/+layout.css": {
    "file": "_app/immutable/assets/_layout-2ee860c0.css",
    "src": "src/routes/+layout.css"
  }
}